genexpy/__init__.py
genexpy/kernels/__init__.py
genexpy/kernels/base.py
genexpy/kernels/rankings.py
genexpy/kernels/utils.py
genexpy/kernels/vectors.py
genexpy/managers.py
genexpy/random.py
genexpy/utils/__init__.py
genexpy/utils/rankings.py
genexpy/utils/relations.py
genexpy-1.0.2a1.dist-info/licenses/LICENSE.md
genexpy-1.0.2a1.dist-info/METADATA
genexpy-1.0.2a1.dist-info/WHEEL
genexpy-1.0.2a1.dist-info/RECORD
