Metadata-Version: 2.4
Name: genexpy
Version: 1.0.2a1
Summary: Generalizability of experimental studies and rankings utilies
License: MIT
License-File: LICENSE.md
Keywords: generalizability,experiments,evaluation,statistics
Author: Federico Matteucci
Author-email: federico.matteucci@kit.edu
Requires-Python: >=3.13
Classifier: Development Status :: 5 - Production/Stable
Classifier: Intended Audience :: Science/Research
Classifier: License :: OSI Approved :: MIT License
Classifier: Topic :: Education
Classifier: Topic :: Scientific/Engineering :: Information Analysis
Classifier: Topic :: Scientific/Engineering :: Mathematics
Requires-Dist: matplotlib (>=3.10)
Requires-Dist: numpy (>=2.3)
Requires-Dist: pandas (>=2.3)
Requires-Dist: pyyaml (>=6.0)
Requires-Dist: scikit-learn (>=1.7)
Requires-Dist: scipy (>=1.16)
Requires-Dist: seaborn (>=0.13)
Requires-Dist: tqdm (>=4.67)
Project-URL: Bug Tracker, https://github.com/DrCohomology/genexpy/issues
Project-URL: Documentation, https://github.com/DrCohomology/genexpy
Project-URL: Homepage, https://github.com/DrCohomology/genexpy
Project-URL: Repository, https://github.com/DrCohomology/genexpy
